pysensedf/__init__.py
pysensedf/ai/__init__.py
pysensedf/ai/cleaner_ai.py
pysensedf/ai/feature_ai.py
pysensedf/ai/nlp.py
pysensedf/ai/recommender.py
pysensedf/core/__init__.py
pysensedf/core/dataframe.py
pysensedf/core/sql_translator.py
pysensedf/datasets/__init__.py
pysensedf/datasets/customers.csv
pysensedf/datasets/products.csv
pysensedf/datasets/sales.csv
pysensedf/integrations/__init__.py
pysensedf/integrations/pipelinescript_integration.py
pysensedf/io/__init__.py
pysensedf/ml/__init__.py
pysensedf/utils/__init__.py
pysensedf-0.4.1.dist-info/licenses/LICENSE
pysensedf-0.4.1.dist-info/METADATA
pysensedf-0.4.1.dist-info/WHEEL
pysensedf-0.4.1.dist-info/top_level.txt
pysensedf-0.4.1.dist-info/RECORD
