Metadata-Version: 2.4
Name: pysensedf
Version: 0.4.1
Summary: PySenseDF — AI-powered Python DataFrame that beats Pandas - Monte Carlo simulation, 27-92x faster with smart caching & NumPy backend
Home-page: https://github.com/idrissbado/PySenseDF
Author: Idriss Bado
Author-email: Idriss Bado <idrissbadoolivier@gmail.com>
License: MIT
Project-URL: Homepage, https://github.com/idrissbado/PySenseDF
Project-URL: Documentation, https://github.com/idrissbado/PySenseDF/blob/main/README.md
Project-URL: Repository, https://github.com/idrissbado/PySenseDF
Project-URL: Issues, https://github.com/idrissbado/PySenseDF/issues
Keywords: dataframe,pandas,data-analysis,ai,ml,sql,lazy-evaluation,data-science
Classifier: Development Status :: 4 - Beta
Classifier: Intended Audience :: Developers
Classifier: Intended Audience :: Science/Research
Classifier: Topic :: Scientific/Engineering
Classifier: Topic :: Software Development :: Libraries :: Python Modules
Classifier: License :: OSI Approved :: MIT License
Classifier: Programming Language :: Python :: 3
Classifier: Programming Language :: Python :: 3.8
Classifier: Programming Language :: Python :: 3.9
Classifier: Programming Language :: Python :: 3.10
Classifier: Programming Language :: Python :: 3.11
Classifier: Programming Language :: Python :: 3.12
Classifier: Operating System :: OS Independent
Requires-Python: >=3.8
License-File: LICENSE
Provides-Extra: perf
Requires-Dist: numpy>=1.21.0; extra == "perf"
Requires-Dist: numba>=0.55.0; extra == "perf"
Provides-Extra: ml
Requires-Dist: scikit-learn>=1.0.0; extra == "ml"
Requires-Dist: xgboost>=1.5.0; extra == "ml"
Provides-Extra: ai
Requires-Dist: transformers>=4.20.0; extra == "ai"
Requires-Dist: torch>=1.12.0; extra == "ai"
Provides-Extra: cloud
Requires-Dist: boto3>=1.20.0; extra == "cloud"
Requires-Dist: azure-storage-blob>=12.0.0; extra == "cloud"
Requires-Dist: google-cloud-storage>=2.0.0; extra == "cloud"
Provides-Extra: data
Requires-Dist: pyarrow>=6.0.0; extra == "data"
Requires-Dist: openpyxl>=3.0.0; extra == "data"
Requires-Dist: sqlalchemy>=1.4.0; extra == "data"
Provides-Extra: full
Requires-Dist: numpy>=1.21.0; extra == "full"
Requires-Dist: numba>=0.55.0; extra == "full"
Requires-Dist: scikit-learn>=1.0.0; extra == "full"
Requires-Dist: pyarrow>=6.0.0; extra == "full"
Requires-Dist: openpyxl>=3.0.0; extra == "full"
Requires-Dist: sqlalchemy>=1.4.0; extra == "full"
Provides-Extra: dev
Requires-Dist: pytest>=7.0.0; extra == "dev"
Requires-Dist: pytest-cov>=3.0.0; extra == "dev"
Requires-Dist: black>=22.0.0; extra == "dev"
Requires-Dist: flake8>=4.0.0; extra == "dev"
Dynamic: author
Dynamic: home-page
Dynamic: license-file
Dynamic: requires-python
